pyteamtv/__init__.py
pyteamtv/dash.py
pyteamtv/dataframe_builder.py
pyteamtv/exceptions.py
pyteamtv/flask.py
pyteamtv/streamlit.py
pyteamtv/_integrations/__init__.py
pyteamtv/_integrations/_flask.py
pyteamtv/_integrations/_streamlit.py
pyteamtv/_integrations/app.py
pyteamtv/api/__init__.py
pyteamtv/api/app.py
pyteamtv/api/endpoint.py
pyteamtv/api/token.py
pyteamtv/api/user.py
pyteamtv/infra/__init__.py
pyteamtv/infra/requester.py
pyteamtv/infra/match_state/__init__.py
pyteamtv/infra/match_state/event_store.py
pyteamtv/infra/match_state/match_config_calculator.py
pyteamtv/infra/match_state/match_event_fetcher.py
pyteamtv/infra/match_state/match_state_calculator.py
pyteamtv/models/__init__.py
pyteamtv/models/access_requester.py
pyteamtv/models/app_storage.py
pyteamtv/models/bulk_observation.py
pyteamtv/models/club.py
pyteamtv/models/custom_tag.py
pyteamtv/models/event_stream.py
pyteamtv/models/exercise.py
pyteamtv/models/line_up.py
pyteamtv/models/list.py
pyteamtv/models/membership.py
pyteamtv/models/membership_list.py
pyteamtv/models/observation.py
pyteamtv/models/observation_log.py
pyteamtv/models/person.py
pyteamtv/models/player.py
pyteamtv/models/playlist.py
pyteamtv/models/sharing_group.py
pyteamtv/models/sporting_event.py
pyteamtv/models/team.py
pyteamtv/models/teamtv_object.py
pyteamtv/models/video.py
pyteamtv/models/match/__init__.py
pyteamtv/models/match/match_config.py
pyteamtv/models/match/match_state.py
pyteamtv/models/resource_group/__init__.py
pyteamtv/models/resource_group/app_developer.py
pyteamtv/models/resource_group/capabilities.py
pyteamtv/models/resource_group/club.py
pyteamtv/models/resource_group/education.py
pyteamtv/models/resource_group/exchange.py
pyteamtv/models/resource_group/factory.py
pyteamtv/models/resource_group/learning_group.py
pyteamtv/models/resource_group/person.py
pyteamtv/models/resource_group/reseller.py
pyteamtv/models/resource_group/sharing_group.py
pyteamtv/models/resource_group/team.py
pyteamtv-0.39.0.dist-info/licenses/LICENSE
pyteamtv-0.39.0.dist-info/METADATA
pyteamtv-0.39.0.dist-info/WHEEL
pyteamtv-0.39.0.dist-info/top_level.txt
pyteamtv-0.39.0.dist-info/RECORD
