Metadata-Version: 2.4
Name: pyteamtv
Version: 0.39.0
Summary: API for TeamTV Platform
Home-page: https://github.com/teamtv/pyteamtv
Author: Koen Vossen
Author-email: info@koenvossen.nl
License: GPL-3
Classifier: Intended Audience :: Developers
Classifier: Intended Audience :: Science/Research
Classifier: Programming Language :: Python :: 3
Classifier: Programming Language :: Python :: 3.6
Classifier: Programming Language :: Python :: 3.7
Classifier: Programming Language :: Python :: 3.8
Classifier: Programming Language :: Python :: 3.9
Classifier: Programming Language :: Python :: 3.10
Classifier: License :: OSI Approved
Classifier: Topic :: Scientific/Engineering
License-File: LICENSE
Requires-Dist: requests>=2.0.0
Requires-Dist: PyJWT>=1.7.1
Requires-Dist: pyjwt[crypto]>=1.7.1
Requires-Dist: tuspy>=1.0.0
Provides-Extra: test
Requires-Dist: pytest; extra == "test"
Requires-Dist: pandas>=1.0.0; extra == "test"
Requires-Dist: requests-mock==1.10.0; extra == "test"
Requires-Dist: kloppy; extra == "test"
Provides-Extra: cache
Requires-Dist: requests-cache>=0.9.7; extra == "cache"
Provides-Extra: kloppy
Requires-Dist: kloppy>=3.0.0; extra == "kloppy"
Dynamic: author
Dynamic: author-email
Dynamic: classifier
Dynamic: description
Dynamic: description-content-type
Dynamic: home-page
Dynamic: license
Dynamic: license-file
Dynamic: provides-extra
Dynamic: requires-dist
Dynamic: summary
